{
  "ok": true,
  "taskid": "dr_dweZGaCBv0OAfzh0liJWA/1OrPUefuurBV69HRhKic__t2_1770346455",
  "jobid": "LiNi0",
  "material_id": null,
  "formula": "LiNi0",
  "elements": null,
  "max_candidates": 5,
  "prefer_stable": true,
  "whitelist_ids": [],
  "primary_material_id": "mp-cfyda",
  "count_selected": 5,
  "items": [
    {
      "material_id": "mp-cfyda",
      "legacy_numeric_id": null,
      "all_ids": [
        "mp-cfyda"
      ],
      "formula_pretty": "Li",
      "elements": [
        "Li"
      ],
      "chemsys": "Li",
      "nsites": 3,
      "density": 0.5649380290750841,
      "volume": 61.205660097660434,
      "energy_above_hull": 0.0,
      "is_stable": true,
      "energy_per_atom": -2.386706413333333,
      "formation_energy_per_atom": 0.0,
      "band_gap": 0.0,
      "symmetry": {
        "crystal_system": "Trigonal",
        "symbol": "R-3m",
        "number": 166
      },
      "database_IDs": {
        "icsd": [
          "icsd-642106",
          "icsd-426951",
          "icsd-642105"
        ]
      },
      "selected_reason": "ranked_topk"
    },
    {
      "material_id": "mp-bz",
      "legacy_numeric_id": null,
      "all_ids": [
        "mp-bz"
      ],
      "formula_pretty": "Li",
      "elements": [
        "Li"
      ],
      "chemsys": "Li",
      "nsites": 1,
      "density": 0.5664547498885351,
      "volume": 20.347259270998425,
      "energy_above_hull": 0.001672373333333,
      "is_stable": false,
      "energy_per_atom": -2.38503404,
      "formation_energy_per_atom": 0.001672373333333,
      "band_gap": 0.0,
      "symmetry": {
        "crystal_system": "Cubic",
        "symbol": "Fm-3m",
        "number": 225
      },
      "database_IDs": {
        "icsd": [
          "icsd-44763",
          "icsd-642110",
          "icsd-57408",
          "icsd-109011",
          "icsd-76948"
        ]
      },
      "selected_reason": "ranked_topk"
    },
    {
      "material_id": "mp-cdokh",
      "legacy_numeric_id": null,
      "all_ids": [
        "mp-cdokh"
      ],
      "formula_pretty": "Li",
      "elements": [
        "Li"
      ],
      "chemsys": "Li",
      "nsites": 4,
      "density": 0.5659385321116011,
      "volume": 81.46327565480371,
      "energy_above_hull": 0.005889090833333,
      "is_stable": false,
      "energy_per_atom": -2.3808173225,
      "formation_energy_per_atom": 0.005889090833333,
      "band_gap": 0.0,
      "symmetry": {
        "crystal_system": "Hexagonal",
        "symbol": "P6_3/mmc",
        "number": 194
      },
      "database_IDs": {},
      "selected_reason": "ranked_topk"
    },
    {
      "material_id": "mp-pbh",
      "legacy_numeric_id": null,
      "all_ids": [
        "mp-pbh"
      ],
      "formula_pretty": "Li",
      "elements": [
        "Li"
      ],
      "chemsys": "Li",
      "nsites": 2,
      "density": 0.573292417154018,
      "volume": 40.20915440845307,
      "energy_above_hull": 0.005987748333333,
      "is_stable": false,
      "energy_per_atom": -2.380718665,
      "formation_energy_per_atom": 0.005987748333333,
      "band_gap": 0.0,
      "symmetry": {
        "crystal_system": "Hexagonal",
        "symbol": "P6_3/mmc",
        "number": 194
      },
      "database_IDs": {
        "icsd": [
          "icsd-20928",
          "icsd-76947",
          "icsd-44760"
        ]
      },
      "selected_reason": "ranked_topk"
    },
    {
      "material_id": "mp-bghgr",
      "legacy_numeric_id": null,
      "all_ids": [
        "mp-bghgr"
      ],
      "formula_pretty": "Li",
      "elements": [
        "Li"
      ],
      "chemsys": "Li",
      "nsites": 8,
      "density": 0.570042740991187,
      "volume": 161.75350839454015,
      "energy_above_hull": 0.008819463333333001,
      "is_stable": false,
      "energy_per_atom": -2.37788695,
      "formation_energy_per_atom": 0.008819463333333001,
      "band_gap": 0.0,
      "symmetry": {
        "crystal_system": "Cubic",
        "symbol": "I-43d",
        "number": 220
      },
      "database_IDs": {
        "icsd": [
          "icsd-109012"
        ]
      },
      "selected_reason": "ranked_topk"
    }
  ]
}