{
  "@module": "pymatgen.core.structure",
  "@class": "Structure",
  "charge": 0,
  "lattice": {
    "matrix": [
      [
        5.58500572,
        -0.0,
        0.0
      ],
      [
        0.0,
        5.77809678,
        0.0
      ],
      [
        0.0,
        0.0,
        8.01738023
      ]
    ],
    "pbc": [
      true,
      true,
      true
    ],
    "a": 5.58500572,
    "b": 5.77809678,
    "c": 8.01738023,
    "alpha": 90.0,
    "beta": 90.0,
    "gamma": 90.0,
    "volume": 258.7265007863652
  },
  "properties": {},
  "sites": [
    {
      "species": [
        {
          "element": "Ca",
          "occu": 1
        }
      ],
      "abc": [
        0.01354358,
        0.9480419,
        0.25
      ],
      "properties": {
        "magmom": -0.0
      },
      "label": "Ca",
      "xyz": [
        0.0756409717692776,
        5.477877849695083,
        2.0043450575
      ]
    },
    {
      "species": [
        {
          "element": "Ca",
          "occu": 1
        }
      ],
      "abc": [
        0.51354358,
        0.5519581,
        0.75
      ],
      "properties": {
        "magmom": -0.0
      },
      "label": "Ca",
      "xyz": [
        2.8681438317692773,
        3.189267320304918,
        6.0130351725
      ]
    },
    {
      "species": [
        {
          "element": "Ca",
          "occu": 1
        }
      ],
      "abc": [
        0.48645642,
        0.4480419,
        0.25
      ],
      "properties": {
        "magmom": -0.0
      },
      "label": "Ca",
      "xyz": [
        2.7168618882307225,
        2.588829459695082,
        2.0043450575
      ]
    },
    {
      "species": [
        {
          "element": "Ca",
          "occu": 1
        }
      ],
      "abc": [
        0.98645642,
        0.0519581,
        0.75
      ],
      "properties": {
        "magmom": -0.0
      },
      "label": "Ca",
      "xyz": [
        5.509364748230722,
        0.30021893030491803,
        6.0130351725
      ]
    },
    {
      "species": [
        {
          "element": "Zr",
          "occu": 1
        }
      ],
      "abc": [
        -0.0,
        0.5,
        0.0
      ],
      "properties": {
        "magmom": -0.0
      },
      "label": "Zr",
      "xyz": [
        0.0,
        2.88904839,
        0.0
      ]
    },
    {
      "species": [
        {
          "element": "Zr",
          "occu": 1
        }
      ],
      "abc": [
        0.5,
        0.0,
        0.0
      ],
      "properties": {
        "magmom": -0.0
      },
      "label": "Zr",
      "xyz": [
        2.79250286,
        0.0,
        0.0
      ]
    },
    {
      "species": [
        {
          "element": "Zr",
          "occu": 1
        }
      ],
      "abc": [
        0.5,
        0.0,
        0.5
      ],
      "properties": {
        "magmom": -0.0
      },
      "label": "Zr",
      "xyz": [
        2.79250286,
        0.0,
        4.008690115
      ]
    },
    {
      "species": [
        {
          "element": "Zr",
          "occu": 1
        }
      ],
      "abc": [
        -0.0,
        0.5,
        0.5
      ],
      "properties": {
        "magmom": -0.0
      },
      "label": "Zr",
      "xyz": [
        0.0,
        2.88904839,
        4.008690115
      ]
    },
    {
      "species": [
        {
          "element": "O",
          "occu": 1
        }
      ],
      "abc": [
        0.30237482,
        0.70030789,
        0.44341551
      ],
      "properties": {
        "magmom": 0.0
      },
      "label": "O",
      "xyz": [
        1.6887650992839702,
        4.0464467642175945,
        3.5550307435493678
      ]
    },
    {
      "species": [
        {
          "element": "O",
          "occu": 1
        }
      ],
      "abc": [
        0.80237482,
        0.7996921100000001,
        0.55658449
      ],
      "properties": {
        "magmom": 0.0
      },
      "label": "O",
      "xyz": [
        4.48126795928397,
        4.620698405782407,
        4.462349486450633
      ]
    },
    {
      "species": [
        {
          "element": "O",
          "occu": 1
        }
      ],
      "abc": [
        0.19762518,
        0.20030789000000002,
        0.05658449
      ],
      "properties": {
        "magmom": 0.0
      },
      "label": "O",
      "xyz": [
        1.1037377607160297,
        1.1573983742175944,
        0.45365937145063273
      ]
    },
    {
      "species": [
        {
          "element": "O",
          "occu": 1
        }
      ],
      "abc": [
        0.6976251800000001,
        0.29969211,
        0.94341551
      ],
      "properties": {
        "magmom": 0.0
      },
      "label": "O",
      "xyz": [
        3.89624062071603,
        1.731650015782406,
        7.563720858549368
      ]
    },
    {
      "species": [
        {
          "element": "O",
          "occu": 1
        }
      ],
      "abc": [
        0.6976251800000001,
        0.29969211,
        0.55658449
      ],
      "properties": {
        "magmom": 0.0
      },
      "label": "O",
      "xyz": [
        3.89624062071603,
        1.731650015782406,
        4.462349486450633
      ]
    },
    {
      "species": [
        {
          "element": "O",
          "occu": 1
        }
      ],
      "abc": [
        0.19762518,
        0.20030789000000002,
        0.44341551
      ],
      "properties": {
        "magmom": 0.0
      },
      "label": "O",
      "xyz": [
        1.1037377607160297,
        1.1573983742175944,
        3.5550307435493678
      ]
    },
    {
      "species": [
        {
          "element": "O",
          "occu": 1
        }
      ],
      "abc": [
        0.80237482,
        0.7996921100000001,
        0.94341551
      ],
      "properties": {
        "magmom": 0.0
      },
      "label": "O",
      "xyz": [
        4.48126795928397,
        4.620698405782407,
        7.563720858549368
      ]
    },
    {
      "species": [
        {
          "element": "O",
          "occu": 1
        }
      ],
      "abc": [
        0.30237482,
        0.70030789,
        0.05658449
      ],
      "properties": {
        "magmom": 0.0
      },
      "label": "O",
      "xyz": [
        1.6887650992839702,
        4.0464467642175945,
        0.45365937145063273
      ]
    },
    {
      "species": [
        {
          "element": "O",
          "occu": 1
        }
      ],
      "abc": [
        0.60684618,
        0.04155889,
        0.25
      ],
      "properties": {
        "magmom": 0.0
      },
      "label": "O",
      "xyz": [
        3.3892393864601496,
        0.2401312884893742,
        2.0043450575
      ]
    },
    {
      "species": [
        {
          "element": "O",
          "occu": 1
        }
      ],
      "abc": [
        0.10684618,
        0.45844111,
        0.75
      ],
      "properties": {
        "magmom": 0.0
      },
      "label": "O",
      "xyz": [
        0.5967365264601496,
        2.6489171015106256,
        6.0130351725
      ]
    },
    {
      "species": [
        {
          "element": "O",
          "occu": 1
        }
      ],
      "abc": [
        0.89315382,
        0.54155889,
        0.25
      ],
      "properties": {
        "magmom": 0.0
      },
      "label": "O",
      "xyz": [
        4.98826919353985,
        3.1291796784893746,
        2.0043450575
      ]
    },
    {
      "species": [
        {
          "element": "O",
          "occu": 1
        }
      ],
      "abc": [
        0.39315382,
        0.95844111,
        0.75
      ],
      "properties": {
        "magmom": 0.0
      },
      "label": "O",
      "xyz": [
        2.1957663335398503,
        5.537965491510626,
        6.0130351725
      ]
    }
  ]
}